atokaconn/__init__.py
atokaconn/cli/__init__.py
atokaconn/cli/companies.py
atokaconn/cli/main.py
atokaconn/cli/people.py
atokaconn-0.1.8.dist-info/entry_points.txt
atokaconn-0.1.8.dist-info/LICENSE.txt
atokaconn-0.1.8.dist-info/WHEEL
atokaconn-0.1.8.dist-info/METADATA
atokaconn-0.1.8.dist-info/RECORD
