Metadata-Version: 2.1
Name: atokaconn
Version: 0.1.8
Summary: A package that facilitates connections to and data extractions from the ATOKA API service.
Home-page: https://github.com/openpolis/atokaconn/
License: MIT
Author: guglielmo
Author-email: guglielmo@openpolis.it
Requires-Python: >=3.6,<4.0
Classifier: License :: OSI Approved :: MIT License
Classifier: Programming Language :: Python :: 3
Classifier: Programming Language :: Python :: 3.6
Classifier: Programming Language :: Python :: 3.7
Classifier: Programming Language :: Python :: 3.8
Classifier: Programming Language :: Python :: 3.9
Requires-Dist: Faker (>=8.10.1,<9.0.0)
Requires-Dist: requests (>=2.25.1,<3.0.0)
Requires-Dist: requests-toolbelt (>=0.9.1,<0.10.0)
Requires-Dist: typer (>=0.6.1,<0.7.0)
Project-URL: Repository, https://github.com/openpolis/atokaconn/
